tastytrade/__init__.py
tastytrade/account.py
tastytrade/instruments.py
tastytrade/market_data.py
tastytrade/market_sessions.py
tastytrade/metrics.py
tastytrade/oauth.py
tastytrade/order.py
tastytrade/py.typed
tastytrade/search.py
tastytrade/session.py
tastytrade/streamer.py
tastytrade/utils.py
tastytrade/watchlists.py
tastytrade/dxfeed/__init__.py
tastytrade/dxfeed/candle.py
tastytrade/dxfeed/event.py
tastytrade/dxfeed/greeks.py
tastytrade/dxfeed/profile.py
tastytrade/dxfeed/quote.py
tastytrade/dxfeed/summary.py
tastytrade/dxfeed/theoprice.py
tastytrade/dxfeed/timeandsale.py
tastytrade/dxfeed/trade.py
tastytrade/dxfeed/underlying.py
tastytrade-11.0.3.dist-info/METADATA
tastytrade-11.0.3.dist-info/WHEEL
tastytrade-11.0.3.dist-info/licenses/LICENSE
tastytrade-11.0.3.dist-info/RECORD
