Metadata-Version: 2.4
Name: tastytrade
Version: 11.0.3
Summary: An unofficial, sync/async SDK for Tastytrade!
Project-URL: Homepage, https://github.com/tastyware/tastytrade
Project-URL: Documentation, https://tastyworks-api.rtfd.io
Project-URL: Funding, https://github.com/sponsors/tastyware
Project-URL: Source, https://github.com/tastyware/tastytrade
Project-URL: Changelog, https://github.com/tastyware/tastytrade/releases
Author-email: Graeme Holliday <graeme@tastyware.dev>
License: MIT License
License-File: LICENSE
Classifier: Development Status :: 5 - Production/Stable
Classifier: Environment :: Console
Classifier: Framework :: AsyncIO
Classifier: Intended Audience :: Developers
Classifier: Intended Audience :: Financial and Insurance Industry
Classifier: Intended Audience :: Information Technology
Classifier: License :: OSI Approved :: MIT License
Classifier: Operating System :: MacOS :: MacOS X
Classifier: Operating System :: Microsoft :: Windows
Classifier: Operating System :: POSIX :: Linux
Classifier: Operating System :: Unix
Classifier: Programming Language :: Python
Classifier: Programming Language :: Python :: 3
Classifier: Programming Language :: Python :: 3 :: Only
Classifier: Programming Language :: Python :: 3.10
Classifier: Programming Language :: Python :: 3.11
Classifier: Programming Language :: Python :: 3.12
Classifier: Programming Language :: Python :: 3.13
Classifier: Programming Language :: Python :: 3.14
Classifier: Topic :: Internet :: WWW/HTTP
Classifier: Topic :: Software Development :: Libraries :: Python Modules
Classifier: Typing :: Typed
Requires-Python: >=3.9
Requires-Dist: httpx>=0.28.1
Requires-Dist: pandas-market-calendars>=5.1.1
Requires-Dist: pydantic>=2.11.9
Requires-Dist: websockets>=15.0.1
